trainer/README.md
trainer/VERSION
trainer/__init__.py
trainer/callbacks.py
trainer/distribute.py
trainer/generic_utils.py
trainer/io.py
trainer/logger.py
trainer/model.py
trainer/torch.py
trainer/trainer.py
trainer/trainer_utils.py
trainer/logging/__init__.py
trainer/logging/aim_logger.py
trainer/logging/base_dash_logger.py
trainer/logging/clearml_logger.py
trainer/logging/console_logger.py
trainer/logging/dummy_logger.py
trainer/logging/mlflow_logger.py
trainer/logging/tensorboard_logger.py
trainer/logging/wandb_logger.py
trainer/utils/__init__.py
trainer/utils/distributed.py
trainer4win-0.0.7.dist-info/METADATA
trainer4win-0.0.7.dist-info/WHEEL
trainer4win-0.0.7.dist-info/top_level.txt
trainer4win-0.0.7.dist-info/RECORD
